setup.py
chainop/__init__.py
chainop/chainop.py
chainop.egg-info/PKG-INFO
chainop.egg-info/SOURCES.txt
chainop.egg-info/dependency_links.txt
chainop.egg-info/requires.txt
chainop.egg-info/top_level.txt