Metadata-Version: 2.1
Name: chainop
Version: 1.0.1
Summary: Simple method-chaining tool
Home-page: UNKNOWN
Author: Perzan
Author-email: PerzanDevelopment@gmail.com
License: UNKNOWN
Platform: UNKNOWN
